smart_find/__init__.py
smart_find/__main__.py
smart_find-1.0.5.dist-info/LICENSE
smart_find-1.0.5.dist-info/METADATA
smart_find-1.0.5.dist-info/WHEEL
smart_find-1.0.5.dist-info/entry_points.txt
smart_find-1.0.5.dist-info/top_level.txt
smart_find-1.0.5.dist-info/RECORD
