Metadata-Version: 2.1
Name: smart-find
Version: 1.0.5
Summary: smart-find makes it easier to access the advanced features of find and grep
Author-email: Barry Scott <barry@barrys-emacs.org>
License: Apache-2.0
Project-URL: Homepage, https://github.com/barry-scott/CLI-tools
Project-URL: Bug Tracker, https://github.com/barry-scott/CLI-tools/issues
Keywords: development
Classifier: Intended Audience :: End Users/Desktop
Classifier: Topic :: Utilities
Classifier: Environment :: Console
Classifier: Programming Language :: Python :: 3
Requires-Python: >=3.10
License-File: LICENSE
Requires-Dist: colour-text
